MANIFEST.in
README.md
requirements.txt
setup.py
django_static_arrive/__init__.py
django_static_arrive/admin.py
django_static_arrive/apps.py
django_static_arrive/models.py
django_static_arrive/tests.py
django_static_arrive/views.py
django_static_arrive.egg-info/PKG-INFO
django_static_arrive.egg-info/SOURCES.txt
django_static_arrive.egg-info/dependency_links.txt
django_static_arrive.egg-info/not-zip-safe
django_static_arrive.egg-info/requires.txt
django_static_arrive.egg-info/top_level.txt
django_static_arrive/migrations/__init__.py
django_static_arrive/static/arrive/arrive.min.js