Metadata-Version: 2.1
Name: django-static-arrive
Version: 2.4.1.0
Summary: Django application contain arrive js files. And arrive js is absorbed in watching for DOM elements creation and removal.
Home-page: UNKNOWN
Author: zencore
Author-email: dobetter@zencore.cn
License: Private
Keywords: django-static-arrive
Platform: UNKNOWN
Classifier: Development Status :: 5 - Production/Stable
Classifier: Intended Audience :: Developers
Classifier: Topic :: Software Development :: Libraries :: Python Modules
Classifier: License :: OSI Approved :: MIT License
Classifier: Programming Language :: Python :: 3
Classifier: Programming Language :: Python :: 3 :: Only
